<annotation>
	<folder>training_dataset</folder>
	<filename>155.JPG</filename>
	<path>/home/ahmad/Desktop/Repos/PathBranch/AD-VEDD/training_dataset/155.JPG</path>
	<source>
		<database>Unknown</database>
	</source>
	<size>
		<width>5472</width>
		<height>3648</height>
		<depth>3</depth>
	</size>
	<segmented>0</segmented>
	<object>
		<name>Car</name>
		<pose>Unspecified</pose>
		<truncated>0</truncated>
		<difficult>0</difficult>
		<bndbox>
			<xmin>247</xmin>
			<ymin>1460</ymin>
			<xmax>1664</xmax>
			<ymax>2087</ymax>
		</bndbox>
	</object>
	<object>
		<name>Car</name>
		<pose>Unspecified</pose>
		<truncated>0</truncated>
		<difficult>0</difficult>
		<bndbox>
			<xmin>1947</xmin>
			<ymin>1282</ymin>
			<xmax>3341</xmax>
			<ymax>2071</ymax>
		</bndbox>
	</object>
	<object>
		<name>Car</name>
		<pose>Unspecified</pose>
		<truncated>0</truncated>
		<difficult>0</difficult>
		<bndbox>
			<xmin>3564</xmin>
			<ymin>1348</ymin>
			<xmax>5064</xmax>
			<ymax>2026</ymax>
		</bndbox>
	</object>
	<object>
		<name>LaneMark</name>
		<pose>Unspecified</pose>
		<truncated>0</truncated>
		<difficult>0</difficult>
		<bndbox>
			<xmin>2736</xmin>
			<ymin>1343</ymin>
			<xmax>3380</xmax>
			<ymax>1443</ymax>
		</bndbox>
	</object>
	<object>
		<name>LaneMark</name>
		<pose>Unspecified</pose>
		<truncated>0</truncated>
		<difficult>0</difficult>
		<bndbox>
			<xmin>186</xmin>
			<ymin>1332</ymin>
			<xmax>2025</xmax>
			<ymax>1443</ymax>
		</bndbox>
	</object>
</annotation>
