<annotation>
	<folder>training_dataset</folder>
	<filename>92.jpeg</filename>
	<path>/home/ahmad/Desktop/Repos/PathBranch/AD-VEDD/training_dataset/92.jpeg</path>
	<source>
		<database>Unknown</database>
	</source>
	<size>
		<width>0</width>
		<height>0</height>
		<depth>3</depth>
	</size>
	<segmented>0</segmented>
	<object>
		<name>Car</name>
		<pose>Unspecified</pose>
		<truncated>0</truncated>
		<difficult>0</difficult>
		<bndbox>
			<xmin>2223</xmin>
			<ymin>368</ymin>
			<xmax>2894</xmax>
			<ymax>1304</ymax>
		</bndbox>
	</object>
</annotation>
